pyLoadModularJson/__init__.py
pyLoadModularJson/pyLoadModularJson.py
pyLoadModularJson-0.9.1.dist-info/LICENCE
pyLoadModularJson-0.9.1.dist-info/METADATA
pyLoadModularJson-0.9.1.dist-info/WHEEL
pyLoadModularJson-0.9.1.dist-info/top_level.txt
pyLoadModularJson-0.9.1.dist-info/RECORD
