Metadata-Version: 2.1
Name: pyLoadModularJson
Version: 0.9.1
Summary: Load nested JSON files into a dictionary
Home-page: https://github.com/mugpahug/pyLoadModularJson
Author: Edwin Peters
Author-email: edwin.g.w.peters@gmail.com
License: MIT
Keywords: json,config,modular,nested
Platform: UNKNOWN
Classifier: Development Status :: 4 - Beta
Classifier: Intended Audience :: Developers
Classifier: Topic :: Software Development :: Libraries
Classifier: Topic :: System :: Hardware
Classifier: License :: OSI Approved :: MIT License
Classifier: Programming Language :: Python :: 3
Classifier: Programming Language :: Python :: 3.5
License-File: LICENCE
Requires-Dist: rjsmin
Requires-Dist: json5
